salbpone/__init__.py
salbpone/checkers.py
salbpone/constraints_generator.py
salbpone/data_types.py
salbpone/latex_converter.py
salbpone/logger_setup.py
salbpone/slide_generator.py
salbpone/solver.py
salbpone/statement_generator.py
salbpone-24.7.5.dist-info/LICENSE
salbpone-24.7.5.dist-info/METADATA
salbpone-24.7.5.dist-info/WHEEL
salbpone-24.7.5.dist-info/top_level.txt
salbpone-24.7.5.dist-info/RECORD
