Metadata-Version: 2.1
Name: salbpone
Version: 24.7.5
Summary: Simple Assembly Line Balancing Problem (SALBP-1) solver
Author: Oleh Oleinikov
Author-email: Oleh Oleinikov <oleh.oleynikov@gmail.com>
License: GNU GPL v3
Project-URL: Homepage, https://github.com/OlehOleinikov/salbone
Project-URL: Documentation, https://salbpone.readthedocs.io
Keywords: assembly line balancing,SALBP-1,optimization,linear programming,operations research,workstation assignment,combinatorial optimization
Classifier: Intended Audience :: Developers
Classifier: Intended Audience :: Education
Classifier: Intended Audience :: Science/Research
Classifier: Operating System :: OS Independent
Classifier: Natural Language :: Ukrainian
Classifier: Programming Language :: Python :: 3
Classifier: Programming Language :: Python :: 3.10
Classifier: License :: OSI Approved :: GNU General Public License v3 (GPLv3)
Requires-Python: >=3.10
License-File: LICENSE
Requires-Dist: PuLP ~=2.8.0
Requires-Dist: loguru ~=0.7.2
Requires-Dist: networkx ~=3.3
Requires-Dist: pyvis ~=0.3.2
Requires-Dist: numpy ~=2.0.0
Provides-Extra: dev
Requires-Dist: jupyter ; extra == 'dev'
Requires-Dist: sphinx ; extra == 'dev'
Requires-Dist: sphinx-rtd-theme ; extra == 'dev'
Requires-Dist: sphinx-copybutton ; extra == 'dev'
Requires-Dist: sphinx-toggleprompt ; extra == 'dev'
Requires-Dist: sphinx-automodapi ; extra == 'dev'
Requires-Dist: readthedocs-sphinx-search ; extra == 'dev'
Requires-Dist: recommonmark ; extra == 'dev'
